[
	{
		"0": {
			"id": "1",
			"seo_identifier": "fashion",
			"name": "Fashion",
			"offer_count": "2203",
			"image_url": "https://cd-static-001.s3.amazonaws.com/sitespecific/in/coupon-categories/fd002aa03f01a72f938ddcb5ad9fcea5/cover-1140x355.jpg?748246"
		},
		"subCategories": [
			{
				"id": "22",
				"seo_identifier": "clothing",
				"name": "Clothing",
				"offer_count": "1564"
			},
			{
				"id": "23",
				"seo_identifier": "footwear",
				"name": "Footwear",
				"offer_count": "436"
			},
			{
				"id": "25",
				"seo_identifier": "bag-and-accessory",
				"name": "Bags & Accessories",
				"offer_count": "486"
			},
			{
				"id": "24",
				"seo_identifier": "watches-and-sunglasses",
				"name": "Watch & Sunglasses",
				"offer_count": "323"
			},
			{
				"id": "89",
				"seo_identifier": "lingerie",
				"name": "Lingerie",
				"offer_count": "132"
			},
			{
				"id": "102",
				"seo_identifier": "travel-accessories",
				"name": "Travel Accessories",
				"offer_count": "84"
			}
		]
	},
	{
		"0": {
			"id": "2",
			"seo_identifier": "travel",
			"name": "Travel",
			"offer_count": "501",
			"image_url": "https://cd-static-001.s3.amazonaws.com/sitespecific/in/coupon-categories/fd002aa03f01a72f938ddcb5ad9fcea5/cover-1140x355.jpg?748246"
		},
		"subCategories": [
			{
				"id": "26",
				"seo_identifier": "flight",
				"name": "Flight",
				"offer_count": "146"
			},
			{
				"id": "27",
				"seo_identifier": "hotel",
				"name": "Hotel",
				"offer_count": "162"
			},
			{
				"id": "29",
				"seo_identifier": "bus",
				"name": "Bus",
				"offer_count": "60"
			},
			{
				"id": "96",
				"seo_identifier": "cabs",
				"name": "Cabs",
				"offer_count": "50"
			},
			{
				"id": "92",
				"seo_identifier": "railway-bookings",
				"name": "Railway Bookings",
				"offer_count": "13"
			},
			{
				"id": "28",
				"seo_identifier": "holiday",
				"name": "Holiday",
				"offer_count": "74"
			},
			{
				"id": "98",
				"seo_identifier": "self-drive-cars",
				"name": "Self-drive Cars",
				"offer_count": "18"
			},
			{
				"id": "30",
				"seo_identifier": "car-rentals",
				"name": "Car Rentals",
				"offer_count": "44"
			}
		]
	},
	{
		"0": {
			"id": "3",
			"seo_identifier": "food-and-dining",
			"name": "Food & Dining",
			"offer_count": "594",
			"image_url": "https://s3-ap-southeast-1.amazonaws.com/cd-temp-bucket/sitespecific/in/coupon-categories/web/5f735b1ef3026be39a6d1c66e7fe4a19/food-and-dining-cover-large.jpg?80295"
		},
		"subCategories": [
			{
				"id": "95",
				"seo_identifier": "food-ordering",
				"name": "Food Ordering",
				"offer_count": "231"
			},
			{
				"id": "32",
				"seo_identifier": "pizza",
				"name": "Pizza",
				"offer_count": "36"
			},
			{
				"id": "33",
				"seo_identifier": "grocery",
				"name": "Grocery",
				"offer_count": "228"
			},
			{
				"id": "31",
				"seo_identifier": "restaurants",
				"name": "Restaurants",
				"offer_count": "113"
			},
			{
				"id": "34",
				"seo_identifier": "drinks-and-beverages",
				"name": "Drinks & Beverages",
				"offer_count": "66"
			}
		]
	},
	{
		"0": {
			"id": "4",
			"seo_identifier": "mobiles-and-tablets",
			"name": "Mobiles & Tablets",
			"offer_count": "445",
			"image_url": "https://cd-static-001.s3.amazonaws.com/sitespecific/in/coupon-categories/fd002aa03f01a72f938ddcb5ad9fcea5/cover-1140x355.jpg?748246"
		},
		"subCategories": [
			{
				"id": "35",
				"seo_identifier": "mobile",
				"name": "Mobile",
				"offer_count": "209"
			},
			{
				"id": "37",
				"seo_identifier": "mobile-and-tablet-accessories",
				"name": "Mobile & Tablet Accessories",
				"offer_count": "269"
			},
			{
				"id": "36",
				"seo_identifier": "tablet",
				"name": "Tablet",
				"offer_count": "47"
			}
		]
	},
	{
		"0": {
			"id": "20",
			"seo_identifier": "recharges",
			"name": "Recharge",
			"offer_count": "128",
			"image_url": "https://s3-ap-southeast-1.amazonaws.com/cd-temp-bucket/sitespecific/in/coupon-categories/web/7aba9b78eb4dfc382756625e31bc214a/recharges-cover-large.jpg?213356"
		},
		"subCategories": [
			{
				"id": "84",
				"seo_identifier": "mobile-recharge",
				"name": "Mobile Recharge",
				"offer_count": "77"
			},
			{
				"id": "93",
				"seo_identifier": "bill-payments",
				"name": "Bill Payments",
				"offer_count": "62"
			},
			{
				"id": "85",
				"seo_identifier": "dth",
				"name": "DTH",
				"offer_count": "45"
			}
		]
	},
	{
		"0": {
			"id": "5",
			"seo_identifier": "computers-laptops-and-gaming",
			"name": "Computers, Laptops & Gaming",
			"offer_count": "214",
			"image_url": "https://s3-ap-southeast-1.amazonaws.com/cd-temp-bucket/sitespecific/in/coupon-categories/web/b135d8ce4fb93dbe095e4e31b18a621d/computers-laptops-and-gaming-cover-large.png?761533"
		},
		"subCategories": [
			{
				"id": "39",
				"seo_identifier": "computer-accessories",
				"name": "Computer Accessories",
				"offer_count": "147"
			},
			{
				"id": "38",
				"seo_identifier": "laptops-monitors-and-desktops",
				"name": "Laptops, Monitors & Desktops",
				"offer_count": "67"
			},
			{
				"id": "40",
				"seo_identifier": "software",
				"name": "Software",
				"offer_count": "24"
			},
			{
				"id": "41",
				"seo_identifier": "gaming",
				"name": "Gaming",
				"offer_count": "28"
			}
		]
	},
	{
		"0": {
			"id": "13",
			"seo_identifier": "beauty-and-health",
			"name": "Beauty & Health",
			"offer_count": "713",
			"image_url": "https://cd-static-001.s3.amazonaws.com/sitespecific/in/coupon-categories/fd002aa03f01a72f938ddcb5ad9fcea5/cover-1140x355.jpg?748246"
		},
		"subCategories": [
			{
				"id": "67",
				"seo_identifier": "personal-care-and-beauty",
				"name": "Personal Care & Beauty",
				"offer_count": "416"
			},
			{
				"id": "65",
				"seo_identifier": "nutrition",
				"name": "Nutrition",
				"offer_count": "172"
			},
			{
				"id": "64",
				"seo_identifier": "perfumes-and-deos",
				"name": "Perfumes & Deos",
				"offer_count": "84"
			},
			{
				"id": "66",
				"seo_identifier": "health-devices",
				"name": "Health Devices",
				"offer_count": "85"
			},
			{
				"id": "94",
				"seo_identifier": "eyewear",
				"name": "Eyewear",
				"offer_count": "43"
			},
			{
				"id": "68",
				"seo_identifier": "sexual-wellness",
				"name": "Sexual Wellness",
				"offer_count": "22"
			}
		]
	},
	{
		"0": {
			"id": "8",
			"seo_identifier": "appliances",
			"name": "Appliances",
			"offer_count": "190",
			"image_url": "https://s3-ap-southeast-1.amazonaws.com/cd-temp-bucket/sitespecific/in/coupon-categories/web/ef988117becd8cd60924ff5b97c73e43/appliances-cover-large.png?78348"
		},
		"subCategories": [
			{
				"id": "48",
				"seo_identifier": "personal-care-appliances",
				"name": "Personal Care Appliances",
				"offer_count": "47"
			},
			{
				"id": "50",
				"seo_identifier": "home-appliances",
				"name": "Home Appliances",
				"offer_count": "92"
			},
			{
				"id": "49",
				"seo_identifier": "kitchen-appliances",
				"name": "Kitchen Appliances",
				"offer_count": "108"
			},
			{
				"id": "51",
				"seo_identifier": "cleaning-accessories",
				"name": "Cleaning Accessories",
				"offer_count": "24"
			}
		]
	},
	{
		"0": {
			"id": "7",
			"seo_identifier": "cameras-and-accessories",
			"name": "Cameras & Accessories",
			"offer_count": "41",
			"image_url": "https://s3-ap-southeast-1.amazonaws.com/cd-temp-bucket/sitespecific/in/coupon-categories/web/ce12742477fafbb4e225faad6801c267/cameras-and-accessories-cover-large.jpg?923158"
		},
		"subCategories": [
			{
				"id": "46",
				"seo_identifier": "cameras",
				"name": "Cameras",
				"offer_count": "28"
			},
			{
				"id": "47",
				"seo_identifier": "camera-accessories",
				"name": "Camera Accessories",
				"offer_count": "32"
			}
		]
	},
	{
		"0": {
			"id": "11",
			"seo_identifier": "entertainment",
			"name": "Entertainment",
			"offer_count": "103",
			"image_url": "https://cd-static-001.s3.amazonaws.com/sitespecific/in/coupon-categories/fd002aa03f01a72f938ddcb5ad9fcea5/cover-1140x355.jpg?748246"
		},
		"subCategories": [
			{
				"id": "57",
				"seo_identifier": "cinema",
				"name": "Cinema",
				"offer_count": "47"
			},
			{
				"id": "59",
				"seo_identifier": "theme-parks",
				"name": "Theme Parks",
				"offer_count": "34"
			},
			{
				"id": "58",
				"seo_identifier": "indoor-and-outdoor-games",
				"name": "Indoor & Outdoor Games",
				"offer_count": "33"
			}
		]
	},
	{
		"0": {
			"id": "9",
			"seo_identifier": "home-furnishing-and-decor",
			"name": "Home Furnishing & Decor",
			"offer_count": "550",
			"image_url": "https://cd-static-001.s3.amazonaws.com/sitespecific/in/coupon-categories/fd002aa03f01a72f938ddcb5ad9fcea5/cover-1140x355.jpg?748246"
		},
		"subCategories": [
			{
				"id": "53",
				"seo_identifier": "furniture-and-decor",
				"name": "Furniture & Decor",
				"offer_count": "369"
			},
			{
				"id": "54",
				"seo_identifier": "kitchen-and-dining",
				"name": "Kitchen & Dining",
				"offer_count": "162"
			},
			{
				"id": "52",
				"seo_identifier": "bed-and-bath",
				"name": "Bed & Bath",
				"offer_count": "141"
			},
			{
				"id": "97",
				"seo_identifier": "tools",
				"name": "Tools",
				"offer_count": "50"
			}
		]
	},
	{
		"0": {
			"id": "17",
			"seo_identifier": "miscellaneous",
			"name": "Miscellaneous",
			"offer_count": "634",
			"image_url": "https://cd-static-001.s3.amazonaws.com/sitespecific/in/coupon-categories/fd002aa03f01a72f938ddcb5ad9fcea5/cover-1140x355.jpg?748246"
		},
		"subCategories": [
			{
				"id": "82",
				"seo_identifier": "others",
				"name": "Others",
				"offer_count": "495"
			},
			{
				"id": "83",
				"seo_identifier": "pet-products",
				"name": "Pet products",
				"offer_count": "75"
			},
			{
				"id": "79",
				"seo_identifier": "salon-and-spa",
				"name": "Salon & Spa",
				"offer_count": "39"
			},
			{
				"id": "77",
				"seo_identifier": "matrimonial",
				"name": "Matrimonial",
				"offer_count": "14"
			},
			{
				"id": "78",
				"seo_identifier": "astrology",
				"name": "Astrology",
				"offer_count": "12"
			}
		]
	},
	{
		"0": {
			"id": "15",
			"seo_identifier": "gifts-and-jewellery",
			"name": "Flowers, Gifts & Jewellery",
			"offer_count": "701",
			"image_url": "https://cd-static-001.s3.amazonaws.com/sitespecific/in/coupon-categories/fd002aa03f01a72f938ddcb5ad9fcea5/cover-1140x355.jpg?748246"
		},
		"subCategories": [
			{
				"id": "74",
				"seo_identifier": "jewellery",
				"name": "Jewellery",
				"offer_count": "387"
			},
			{
				"id": "71",
				"seo_identifier": "gifts",
				"name": "Gifts",
				"offer_count": "237"
			},
			{
				"id": "72",
				"seo_identifier": "flowers-and-cakes",
				"name": "Flowers & Cakes",
				"offer_count": "148"
			},
			{
				"id": "73",
				"seo_identifier": "gold-coins-and-bars",
				"name": "Gold Coins & Bars",
				"offer_count": "6"
			}
		]
	},
	{
		"0": {
			"id": "12",
			"seo_identifier": "kids-babies-and-toys",
			"name": "Kids, Babies & Toys",
			"offer_count": "207",
			"image_url": "https://cd-static-001.s3.amazonaws.com/sitespecific/in/coupon-categories/fd002aa03f01a72f938ddcb5ad9fcea5/cover-1140x355.jpg?748246"
		},
		"subCategories": [
			{
				"id": "63",
				"seo_identifier": "baby-products",
				"name": "Baby Products",
				"offer_count": "71"
			},
			{
				"id": "61",
				"seo_identifier": "apparel-and-accessories",
				"name": "Apparel & Accessories",
				"offer_count": "92"
			},
			{
				"id": "60",
				"seo_identifier": "toys-and-games",
				"name": "Toys & Games",
				"offer_count": "67"
			},
			{
				"id": "62",
				"seo_identifier": "school-essentials",
				"name": "School Essentials",
				"offer_count": "25"
			}
		]
	},
	{
		"0": {
			"id": "6",
			"seo_identifier": "tv-audio-video-and-movies",
			"name": "TV, Audio/Video & Movies",
			"offer_count": "135",
			"image_url": "https://cd-static-001.s3.amazonaws.com/sitespecific/in/coupon-categories/fd002aa03f01a72f938ddcb5ad9fcea5/cover-1140x355.jpg?748246"
		},
		"subCategories": [
			{
				"id": "42",
				"seo_identifier": "televisions",
				"name": "Televisions",
				"offer_count": "32"
			},
			{
				"id": "43",
				"seo_identifier": "audio-and-video",
				"name": "Audio & Video",
				"offer_count": "32"
			},
			{
				"id": "45",
				"seo_identifier": "music",
				"name": "Music",
				"offer_count": "37"
			},
			{
				"id": "44",
				"seo_identifier": "movies-and-tv-shows",
				"name": "Movies & TV Shows",
				"offer_count": "29"
			},
			{
				"id": "101",
				"seo_identifier": "on-demand-content",
				"name": "On Demand Content",
				"offer_count": "28"
			},
			{
				"id": "100",
				"seo_identifier": "dth-internet",
				"name": "DTH & Internet Providers",
				"offer_count": "17"
			}
		]
	},
	{
		"0": {
			"id": "10",
			"seo_identifier": "books-and-stationary",
			"name": "Books & Stationery",
			"offer_count": "178",
			"image_url": "https://cd-static-001.s3.amazonaws.com/sitespecific/in/coupon-categories/fd002aa03f01a72f938ddcb5ad9fcea5/cover-1140x355.jpg?748246"
		},
		"subCategories": [
			{
				"id": "55",
				"seo_identifier": "books-ebooks-and-magazines",
				"name": "Books, eBooks & Magazines",
				"offer_count": "71"
			},
			{
				"id": "56",
				"seo_identifier": "posters-and-stationery",
				"name": "Posters & Stationery",
				"offer_count": "118"
			}
		]
	},
	{
		"0": {
			"id": "14",
			"seo_identifier": "sports-and-fitness",
			"name": "Sports & Fitness",
			"offer_count": "131",
			"image_url": "https://cd-static-001.s3.amazonaws.com/sitespecific/in/coupon-categories/fd002aa03f01a72f938ddcb5ad9fcea5/cover-1140x355.jpg?748246"
		},
		"subCategories": [
			{
				"id": "70",
				"seo_identifier": "sports-apparel-and-equipment",
				"name": "Sports Apparel & Equipment",
				"offer_count": "116"
			},
			{
				"id": "69",
				"seo_identifier": "fitness-equipment",
				"name": "Fitness Equipment",
				"offer_count": "24"
			}
		]
	},
	{
		"0": {
			"id": "16",
			"seo_identifier": "automotive",
			"name": "Automotive",
			"offer_count": "72",
			"image_url": "https://cd-static-001.s3.amazonaws.com/sitespecific/in/coupon-categories/fd002aa03f01a72f938ddcb5ad9fcea5/cover-1140x355.jpg?748246"
		},
		"subCategories": [
			{
				"id": "76",
				"seo_identifier": "accessories-and-gears",
				"name": "Accessories & Gears",
				"offer_count": "65"
			},
			{
				"id": "75",
				"seo_identifier": "car-electronics",
				"name": "Car Electronics",
				"offer_count": "10"
			}
		]
	},
	{
		"0": {
			"id": "18",
			"seo_identifier": "web-hosting-and-domains",
			"name": "Web Hosting & Domains",
			"offer_count": "71",
			"image_url": "https://cd-static-001.s3.amazonaws.com/sitespecific/in/coupon-categories/fd002aa03f01a72f938ddcb5ad9fcea5/cover-1140x355.jpg?748246"
		},
		"subCategories": [
			{
				"id": "81",
				"seo_identifier": "domains",
				"name": "Domains",
				"offer_count": "32"
			},
			{
				"id": "80",
				"seo_identifier": "web-hosting",
				"name": "Web Hosting",
				"offer_count": "50"
			}
		]
	},
	{
		"0": {
			"id": "19",
			"seo_identifier": "education-and-learning",
			"name": "Education & Learning",
			"offer_count": "90",
			"image_url": "https://cd-static-001.s3.amazonaws.com/sitespecific/in/coupon-categories/fd002aa03f01a72f938ddcb5ad9fcea5/cover-1140x355.jpg?748246"
		},
		"subCategories": [
			{
				"id": "87",
				"seo_identifier": "education",
				"name": "Education",
				"offer_count": "69"
			},
			{
				"id": "86",
				"seo_identifier": "learning",
				"name": "Learning",
				"offer_count": "79"
			}
		]
	},
	{
		"0": {
			"id": "21",
			"seo_identifier": "adult",
			"name": "Adult",
			"offer_count": "29",
			"image_url": "https://cd-static-001.s3.amazonaws.com/sitespecific/in/coupon-categories/fd002aa03f01a72f938ddcb5ad9fcea5/cover-1140x355.jpg?748246"
		},
		"subCategories": [
			{
				"id": "91",
				"seo_identifier": "rummy",
				"name": "Rummy",
				"offer_count": "20"
			},
			{
				"id": "90",
				"seo_identifier": "condom",
				"name": "Condom",
				"offer_count": "2"
			},
			{
				"id": "88",
				"seo_identifier": "wellness",
				"name": "Wellness",
				"offer_count": "7"
			}
		]
	}
]
